{
  "posts": [
    {
      "id": 1,
      "title": "hello"
    },
    {
	"id" : 2 , 
	"title" : "test"
    }
  ],
  "profile": {
    "name": "typicode"
  }, "Categories":[
    {"id": 1, "title": "دارو"},
  {"id": 2, "title": "دارو گیاهی"},
  {"id": 3, "title": "پوست"},
  {"id": 4, "title": "مو"},
  {"id": 5, "title": "مکمل ها"},
  {"id": 6, "title": "دهان و دندان"},
  {"id": 7, "title": "لوازم آرایشی"},
  {"id": 8, "title": "مادر و کودک"},
  {"id": 9, "title": "ویتامین ها"},
  {"id": 10, "title": "محصولات جنسی"},
  {"id": 11, "title": "تجهیزات پزشکی"},
  {"id": 12, "title": "حیوانات"}
  ]
}
